{
  "scanned": true,
  "reminders": {
    "Atlas/Knowledge/How To's/css tip for strings of numbers.md": [
      {
        "title": "remind me",
        "time": "2025-05-09",
        "rowNumber": 2
      }
    ]
  },
  "debug": false,
  "settings": {
    "reminderTime": "09:00",
    "reminderTimeStep": 15,
    "laters": "In 30 minutes\nIn 1 hour\nIn 3 hours\nTomorrow\nNext week",
    "useSystemNotification": false,
    "autoCompleteTrigger": "(@",
    "primaryReminderFormat": "ReminderPluginReminderFormat",
    "enableReminderPluginReminderFormat": true,
    "dateFormat": "YYYY-MM-DD",
    "dateTimeFormat": "YYYY-MM-DD HH:mm",
    "strictDateFormat": false,
    "linkDatesToDailyNotes": true,
    "enableTasksPluginReminderFormat": true,
    "useCustomEmojiForTasksPlugin": true,
    "removeTagsForTasksPlugin": true,
    "enableKanbanPluginReminderFormat": false,
    "editDetectionSec": 10,
    "reminderCheckIntervalSec": 5
  }
}