{
  "main": {
    "id": "896fb77528c50fee",
    "type": "split",
    "children": [
      {
        "id": "68735db216b71643",
        "type": "tabs",
        "children": [
          {
            "id": "f05e2d02192b81cd",
            "type": "leaf",
            "state": {
              "type": "markdown",
              "state": {
                "file": "work/tickets/qsl/spike - qsl project.md",
                "mode": "source",
                "source": false
              }
            }
          }
        ]
      }
    ],
    "direction": "vertical"
  },
  "left": {
    "id": "abf2911f56f916d8",
    "type": "split",
    "children": [
      {
        "id": "396d97731e40095f",
        "type": "tabs",
        "children": [
          {
            "id": "688b3d615137a273",
            "type": "leaf",
            "state": {
              "type": "file-explorer",
              "state": {
                "sortOrder": "alphabetical"
              }
            }
          },
          {
            "id": "2fd0f24bea1de5b8",
            "type": "leaf",
            "state": {
              "type": "bookmarks",
              "state": {}
            }
          },
          {
            "id": "3917ba887ee80a77",
            "type": "leaf",
            "state": {
              "type": "search",
              "state": {
                "query": "",
                "matchingCase": false,
                "explainSearch": false,
                "collapseAll": false,
                "extraContext": false,
                "sortOrder": "alphabetical"
              }
            }
          }
        ]
      }
    ],
    "direction": "horizontal",
    "width": 253.5,
    "collapsed": true
  },
  "right": {
    "id": "0bce692d28de0848",
    "type": "split",
    "children": [
      {
        "id": "65b8ffe11667d608",
        "type": "tabs",
        "children": [
          {
            "id": "f6f930a36f742e62",
            "type": "leaf",
            "state": {
              "type": "backlink",
              "state": {
                "file": "work/tickets/qsl/spike - qsl project.md",
                "collapseAll": true,
                "extraContext": false,
                "sortOrder": "alphabetical",
                "showSearch": false,
                "searchQuery": "",
                "backlinkCollapsed": false,
                "unlinkedCollapsed": false
              }
            }
          },
          {
            "id": "f1b8c0e828ff35ab",
            "type": "leaf",
            "state": {
              "type": "outgoing-link",
              "state": {
                "file": "work/tickets/qsl/spike - qsl project.md",
                "linksCollapsed": false,
                "unlinkedCollapsed": true
              }
            }
          },
          {
            "id": "bae038ccea34ead9",
            "type": "leaf",
            "state": {
              "type": "tag",
              "state": {
                "sortOrder": "frequency",
                "useHierarchy": true
              }
            }
          },
          {
            "id": "cdcbb4753a799e94",
            "type": "leaf",
            "state": {
              "type": "outline",
              "state": {
                "file": "work/tickets/qsl/spike - qsl project.md"
              }
            }
          },
          {
            "id": "208fbde1a3bbc195",
            "type": "leaf",
            "state": {
              "type": "mermaid-toolbar-view",
              "state": {}
            }
          },
          {
            "id": "bf1bb66117c75503",
            "type": "leaf",
            "state": {
              "type": "advanced-tables-toolbar",
              "state": {}
            }
          }
        ]
      }
    ],
    "direction": "horizontal",
    "width": 613.5,
    "collapsed": true
  },
  "left-ribbon": {
    "hiddenItems": {
      "table-editor-obsidian:Advanced Tables Toolbar": false,
      "obsidian-kanban:Create new board": false,
      "audio-recorder:Start/stop recording": false,
      "switcher:Open quick switcher": false,
      "graph:Open graph view": false,
      "canvas:Create new canvas": false,
      "daily-notes:Open today's daily note": false,
      "templates:Insert template": false,
      "command-palette:Open command palette": false,
      "obsidian-excalidraw-plugin:Create new drawing": false,
      "mermaid-tools:Open Mermaid Toolbar": false
    }
  },
  "active": "f05e2d02192b81cd",
  "lastOpenFiles": [
    "2024-07-30.md",
    "Kanban.md",
    "work/tickets/qsl/spike - qsl project.md",
    "tools/typescript.md",
    "Education/Typescript/Learning TypeScript.md",
    "days/2024-07-19.md",
    "work/tickets/qsl/required fields.md",
    "spike - qsl project.md",
    "work/tickets/Wysiwyg replacement.md",
    "work/tickets/add found drawing.md",
    "work/people/Natasa.md",
    "work/people",
    "tools/Confluence.md",
    "tools/javascript.md",
    "days/2024-07-29.md",
    "work/docs/Meilurs Agent.md",
    "work/docs",
    "work/tickets/qsl",
    "home/vsedlar/dev/projects/MeilleursAgents/MALegacy/backyard/templates/admin/passerelle/realtor/listing.html.md",
    "work/entities/contract entity.md",
    "home/vsedlar/dev/projects/MeilleursAgents/MALegacy/backyard/templates/admin/passerelle/realtor",
    "home/vsedlar/dev/projects/MeilleursAgents/MALegacy/backyard/templates/admin/passerelle",
    "home/vsedlar/dev/projects/MeilleursAgents/MALegacy/backyard/templates/admin",
    "home/vsedlar/dev/projects/MeilleursAgents/MALegacy/backyard/templates",
    "home/vsedlar/dev/projects/MeilleursAgents/MALegacy/backyard",
    "home/vsedlar/dev/projects/MeilleursAgents/MALegacy",
    "home/vsedlar/dev/projects/MeilleursAgents/MALegacy.md",
    "home/vsedlar/dev/projects/MeilleursAgents",
    "tools/smalltalk.md",
    "days/2024-07-25.md",
    "Education/Typescript/Execute program/Everyday Typescript/quiz.md",
    "Education/Typescript/Execute program/Everyday Typescript/Optional Chaining.md",
    "Education/Typescript/Execute program/Everyday Typescript/EveryDay Typescript.md",
    "Education/Typescript/Execute program/execute program courses.md",
    "2024-07-25.md",
    "work/entities/place entity.md",
    "work/tasks - tickets/qsl.canvas",
    "work/Untitled.canvas",
    "work/CANVAS MAN.canvas"
  ]
}